Workbook

Sheet Résumé
A1: FlowCommerce — suivi
A2: À modifier : onglet Suivi (colonne Statut, nouvelles lignes) et onglet Retours de test. Ce tableau se calcule seul.
A4: Version | B4: À faire | C4: En cours | D4: En test | E4: Fait | F4: Total | G4: Avancement
A5: 1.0.0 | B5: =COUNTIFS(Suivi!$B$2:$B$300,$A5,Suivi!$F$2:$F$300,"À faire") | C5: =COUNTIFS(Suivi!$B$2:$B$300,$A5,Suivi!$F$2:$F$300,"En cours") | D5: =COUNTIFS(Suivi!$B$2:$B$300,$A5,Suivi!$F$2:$F$300,"En test") | E5: =COUNTIFS(Suivi!$B$2:$B$300,$A5,Suivi!$F$2:$F$300,"Fait") | F5: =SUM(B5:E5) | G5: =IF(F5=0,0,E5/F5)
A6: 1.0.1 | B6: =COUNTIFS(Suivi!$B$2:$B$300,$A6,Suivi!$F$2:$F$300,"À faire") | C6: =COUNTIFS(Suivi!$B$2:$B$300,$A6,Suivi!$F$2:$F$300,"En cours") | D6: =COUNTIFS(Suivi!$B$2:$B$300,$A6,Suivi!$F$2:$F$300,"En test") | E6: =COUNTIFS(Suivi!$B$2:$B$300,$A6,Suivi!$F$2:$F$300,"Fait") | F6: =SUM(B6:E6) | G6: =IF(F6=0,0,E6/F6)
A7: 1.0.2 | B7: =COUNTIFS(Suivi!$B$2:$B$300,$A7,Suivi!$F$2:$F$300,"À faire") | C7: =COUNTIFS(Suivi!$B$2:$B$300,$A7,Suivi!$F$2:$F$300,"En cours") | D7: =COUNTIFS(Suivi!$B$2:$B$300,$A7,Suivi!$F$2:$F$300,"En test") | E7: =COUNTIFS(Suivi!$B$2:$B$300,$A7,Suivi!$F$2:$F$300,"Fait") | F7: =SUM(B7:E7) | G7: =IF(F7=0,0,E7/F7)
A8: Production | B8: =COUNTIFS(Suivi!$B$2:$B$300,$A8,Suivi!$F$2:$F$300,"À faire") | C8: =COUNTIFS(Suivi!$B$2:$B$300,$A8,Suivi!$F$2:$F$300,"En cours") | D8: =COUNTIFS(Suivi!$B$2:$B$300,$A8,Suivi!$F$2:$F$300,"En test") | E8: =COUNTIFS(Suivi!$B$2:$B$300,$A8,Suivi!$F$2:$F$300,"Fait") | F8: =SUM(B8:E8) | G8: =IF(F8=0,0,E8/F8)
A9: 1.1.0 | B9: =COUNTIFS(Suivi!$B$2:$B$300,$A9,Suivi!$F$2:$F$300,"À faire") | C9: =COUNTIFS(Suivi!$B$2:$B$300,$A9,Suivi!$F$2:$F$300,"En cours") | D9: =COUNTIFS(Suivi!$B$2:$B$300,$A9,Suivi!$F$2:$F$300,"En test") | E9: =COUNTIFS(Suivi!$B$2:$B$300,$A9,Suivi!$F$2:$F$300,"Fait") | F9: =SUM(B9:E9) | G9: =IF(F9=0,0,E9/F9)
A10: 1.2.0 | B10: =COUNTIFS(Suivi!$B$2:$B$300,$A10,Suivi!$F$2:$F$300,"À faire") | C10: =COUNTIFS(Suivi!$B$2:$B$300,$A10,Suivi!$F$2:$F$300,"En cours") | D10: =COUNTIFS(Suivi!$B$2:$B$300,$A10,Suivi!$F$2:$F$300,"En test") | E10: =COUNTIFS(Suivi!$B$2:$B$300,$A10,Suivi!$F$2:$F$300,"Fait") | F10: =SUM(B10:E10) | G10: =IF(F10=0,0,E10/F10)
A11: Plus tard | B11: =COUNTIFS(Suivi!$B$2:$B$300,$A11,Suivi!$F$2:$F$300,"À faire") | C11: =COUNTIFS(Suivi!$B$2:$B$300,$A11,Suivi!$F$2:$F$300,"En cours") | D11: =COUNTIFS(Suivi!$B$2:$B$300,$A11,Suivi!$F$2:$F$300,"En test") | E11: =COUNTIFS(Suivi!$B$2:$B$300,$A11,Suivi!$F$2:$F$300,"Fait") | F11: =SUM(B11:E11) | G11: =IF(F11=0,0,E11/F11)
A12: Total | B12: =SUM(B5:B11) | C12: =SUM(C5:C11) | D12: =SUM(D5:D11) | E12: =SUM(E5:E11) | F12: =SUM(F5:F11) | G12: =IF(F12=0,0,E12/F12)
A14: Retours de test ouverts | B14: =COUNTIFS('Retours de test'!$H$2:$H$300,"<>Fait",'Retours de test'!$D$2:$D$300,"<>")
A16: Réf. AF : voir docs/af-v1.md et docs/af-v2.md. État au 01/10/2026.

Sheet Suivi
A1: ID | B1: Version | C1: Réf. AF | D1: Tâche | E1: Zone | F1: Statut | G1: Priorité | H1: Date de fin | I1: Notes
A2: FC-001 | B2: 1.0.0 | C2: F-01 | D2: Compte : email, Google, mot de passe oublié, vérification email | E2: mobile | F2: Fait | G2: P1
A3: FC-002 | B3: 1.0.0 | C3: F-02 | D3: Plusieurs boutiques, boutique active, sélecteur dans l’en-tête | E3: mobile | F3: Fait | G3: P1
A4: FC-003 | B4: 1.0.0 | C4: F-03 | D4: Produits et catégories (liste standard + ajout), archivage | E4: mobile | F4: Fait | G4: P1
A5: FC-004 | B5: 1.0.0 | C5: F-04 | D5: Mouvements de stock, réapprovisionnement rapide, historique | E5: mobile | F5: Fait | G5: P1
A6: FC-005 | B6: 1.0.0 | C6: F-05 | D6: Clients : plusieurs numéros, profil réseau, appeler / WhatsApp, stats | E6: mobile | F6: Fait | G6: P1
A7: FC-006 | B7: 1.0.0 | C7: F-06 | D7: Nouvelle commande en 4 étapes (client, produits, remise et date, paiement) | E7: mobile | F7: Fait | G7: P1
A8: FC-007 | B8: 1.0.0 | C8: F-07 | D8: Liste et fiche commande : dates, recherche, filtres, retards, Terminées | E8: mobile | F8: Fait | G8: P1
A9: FC-008 | B9: 1.0.0 | C9: F-08 | D9: Dépenses | E9: mobile | F9: Fait | G9: P2
A10: FC-009 | B10: 1.0.0 | C10: F-09 | D10: Tableau de bord : CA, bénéfice, compteurs, À traiter | E10: mobile | F10: Fait | G10: P1
A11: FC-010 | B11: 1.0.0 | C11: — | D11: API Express + Postgres, tests d’intégration (88) | E11: api | F11: Fait | G11: P1
A12: FC-011 | B12: 1.0.0 | C12: — | D12: Déploiement : API Render + base Neon, APK preview EAS | E12: infra | F12: Fait | G12: P1
A13: FC-012 | B13: 1.0.1 | C13: — | D13: Retours de test : polices intégrées, marge basse, clavier, bordures | E13: mobile | F13: Fait | G13: P1 | H13: 01/10/2026 | I13: Testé sur téléphone
A14: FC-013 | B14: 1.0.1 | C14: — | D14: Icône, écran de démarrage et logo de connexion | E14: mobile | F14: Fait | G14: P2 | H14: 01/10/2026
A15: FC-014 | B15: 1.0.1 | C15: — | D15: APK allégé : arm64-v8a + armeabi-v7a, R8 | E15: infra | F15: Fait | G15: P2 | H15: 01/10/2026
A16: FC-015 | B16: 1.0.2 | C16: — | D16: Nouveaux retours de test (à lister dans l’onglet Retours de test) | E16: mobile | F16: À faire | G16: P1
A17: FC-016 | B17: Production | C17: — | D17: Render Starter (7 $/mois) ; Neon payant dès les premiers clients payants | E17: infra | F17: À faire | G17: P1 | I17: Supprime la mise en veille
A18: FC-017 | B18: Production | C18: F-01 | D18: SHA-1 de la clé EAS dans Firebase (Google dans l’APK) | E18: infra | F18: À faire | G18: P1
A19: FC-018 | B19: Production | C19: — | D19: Limite de requêtes (rate limiting) sur l’API | E19: api | F19: À faire | G19: P1
A20: FC-019 | B20: Production | C20: F-03 | D20: Photos : activer Firebase Storage (Blaze), bucket, règles | E20: infra | F20: À faire | G20: P2 | I20: En attendant : sans photo
A21: FC-020 | B21: Production | C21: — | D21: Publication Play Store (compte 25 $, .aab, SHA-1 Google Play) | E21: infra | F21: À faire | G21: P1
A22: FC-021 | B22: Production | C22: F-02 | D22: Logo de chaque boutique dans l’en-tête | E22: mobile | F22: À faire | G22: P3
A23: FC-022 | B23: 1.1.0 | C23: F-15 | D23: Cache persistant : ouverture instantanée avec les dernières données | E23: mobile | F23: À faire | G23: P1
A24: FC-023 | B24: 1.1.0 | C24: F-15 | D24: Réveil de l’API au lancement + bandeau « Hors ligne » | E24: mobile | F24: À faire | G24: P2
A25: FC-024 | B25: 1.2.0 | C25: F-10 | D25: Migration : shop_members, shop_invitations, orders.assigned_to | E25: api | F25: À faire | G25: P1
A26: FC-025 | B26: 1.2.0 | C26: RG-51 | D26: Droits par rôle sur toutes les routes (tests par rôle) | E26: api | F26: À faire | G26: P1
A27: FC-026 | B27: 1.2.0 | C27: F-10 | D27: Endpoints équipe et invitations (propriétaire, gérant → CM) | E27: api | F27: À faire | G27: P1
A28: FC-027 | B28: 1.2.0 | C28: F-12 | D28: Assigner un livreur ; le livreur prend une livraison non assignée | E28: api | F28: À faire | G28: P1
A29: FC-028 | B29: 1.2.0 | C29: F-10 | D29: Écran Équipe : membres, inviter (code), changer de rôle, retirer | E29: mobile | F29: À faire | G29: P1
A30: FC-029 | B30: 1.2.0 | C30: F-11 | D30: Rejoindre une boutique avec un code ; quitter une boutique | E30: mobile | F30: À faire | G30: P1
A31: FC-030 | B31: 1.2.0 | C31: F-13 | D31: Espace livreur : Mes livraisons, À prendre | E31: mobile | F31: À faire | G31: P1
A32: FC-031 | B32: 1.2.0 | C32: F-14 | D32: Navigation et boutons masqués selon le rôle | E32: mobile | F32: À faire | G32: P1
... A35: FC-034 | B35: Plus tard | C35: F-07 | D35: Filtres Commandes « non payées » et « sans client » | E35: api | F35: À faire | G35: P3
A36: FC-035 | B36: Plus tard | C36: RG-24 | D36: Modifier les lignes d’une commande en attente | E36: mobile | F36: À faire | G36: P3 | I36: L’API le permet déjà
A37: FC-036 | B37: Plus tard | C37: — | D37: Mises à jour sans Play Store (EAS Update) | E37: infra | F37: À faire | G37: P2
A38: FC-037 | B38: Plus tard | C38: — | D38: Build Android local (Java 17 + SDK Android, Mac Intel) | E38: infra | F38: À faire | G38: P3

Sheet Retours de test
A1: Date | B1: Version testée | C1: Écran | D1: Problème | E1: Capture (lien) | F1: Gravité | G1: Tâche créée | H1: Statut
A2: 01/10/2026 | B2: 1.0.0 | C2: Connexion | D2: Textes coupés : « Se », « Mot de passe », « Créer un » | F2: Bloquant | G2: FC-012 | H2: Fait
